allograph/__init__.py
allograph/cli.py
allograph/version.py
allograph/core/dynamics/__init__.py
allograph/core/dynamics/base.py
allograph/core/dynamics/diffusion.py
allograph/core/dynamics/discrete.py
allograph/core/graphio/__init__.py
allograph/core/graphio/io.py
allograph/core/graphio/pdb.py
allograph/core/graphio/synth.py
allograph/core/graphio/types.py
allograph/core/inference/__init__.py
allograph/core/inference/forward.py
allograph/core/inference/inverse.py
allograph/core/inference/mediation.py
allograph/core/inference/scan.py
allograph/core/math/laplacian.py
rinet-0.1.9.dist-info/METADATA
rinet-0.1.9.dist-info/WHEEL
rinet-0.1.9.dist-info/entry_points.txt
rinet-0.1.9.dist-info/top_level.txt
rinet-0.1.9.dist-info/RECORD
