Metadata-Version: 2.4
Name: rinet
Version: 0.1.9
Summary: AlloGraph/RINet core library (deterministic residue interaction network inference)
Author: Akul Kumar
Requires-Python: >=3.10
